LICENSE
README.md
setup.py
HiveNetCore/__init__.py
HiveNetCore/cache.py
HiveNetCore/connection_pool.py
HiveNetCore/formula.py
HiveNetCore/generic.py
HiveNetCore/i18n.py
HiveNetCore/logging_hivenet.py
HiveNetCore/parallel.py
HiveNetCore/queue_hivenet.py
HiveNetCore/redirect_stdout.py
HiveNetCore/stream.py
HiveNetCore/xml_hivenet.py
HiveNetCore/yaml.py
HiveNetCore.egg-info/PKG-INFO
HiveNetCore.egg-info/SOURCES.txt
HiveNetCore.egg-info/dependency_links.txt
HiveNetCore.egg-info/entry_points.txt
HiveNetCore.egg-info/not-zip-safe
HiveNetCore.egg-info/requires.txt
HiveNetCore.egg-info/top_level.txt
HiveNetCore/hivenet_error_code/__init__.py
HiveNetCore/hivenet_error_code/errorcode_en.json
HiveNetCore/hivenet_error_code/errorcode_zh.json
HiveNetCore/hivenet_error_code/map_error_code.json
HiveNetCore/utils/__init__.py
HiveNetCore/utils/condition_tool.py
HiveNetCore/utils/debug_tool.py
HiveNetCore/utils/deps_tool.py
HiveNetCore/utils/exception_tool.py
HiveNetCore/utils/file_tool.py
HiveNetCore/utils/global_var_tool.py
HiveNetCore/utils/import_tool.py
HiveNetCore/utils/myzipfile.py
HiveNetCore/utils/net_tool.py
HiveNetCore/utils/pyenv_tool.py
HiveNetCore/utils/run_tool.py
HiveNetCore/utils/string_tool.py
HiveNetCore/utils/test_tool.py
HiveNetCore/utils/validate_tool.py
HiveNetCore/utils/value_tool.py
HiveNetCore/utils/wget.py